pycvi/__init__.py
pycvi/_compare_scores.py
pycvi/_configuration.py
pycvi/_utils.py
pycvi/cluster.py
pycvi/compute_scores.py
pycvi/cvi.py
pycvi/cvi_func.py
pycvi/datasets/Barton/__init__.py
pycvi/datasets/Barton/banana_data.csv
pycvi/datasets/Barton/banana_labels.csv
pycvi/datasets/Barton/diamond9_data.csv
pycvi/datasets/Barton/diamond9_labels.csv
pycvi/datasets/Barton/long1_data.csv
pycvi/datasets/Barton/long1_labels.csv
pycvi/datasets/Barton/target_data.csv
pycvi/datasets/Barton/target_labels.csv
pycvi/datasets/Barton/xclara_data.csv
pycvi/datasets/Barton/xclara_labels.csv
pycvi/datasets/Barton/zelnik1_data.csv
pycvi/datasets/Barton/zelnik1_labels.csv
pycvi/datasets/UCR/SmallKitchenAppliances_data.csv
pycvi/datasets/UCR/SmallKitchenAppliances_labels.csv
pycvi/datasets/UCR/Trace_data.csv
pycvi/datasets/UCR/Trace_labels.csv
pycvi/datasets/UCR/__init__.py
pycvi/datasets/__init__.py
pycvi/datasets/_mini.py
pycvi/datasets/benchmark.py
pycvi/dist.py
pycvi/exceptions.py
pycvi/tests/__init__.py
pycvi/tests/_utils.py
pycvi/tests/test__compare_scores.py
pycvi/tests/test_cluster.py
pycvi/tests/test_compute_scores.py
pycvi/tests/test_cvi.py
pycvi/tests/test_cvi_func.py
pycvi/tests/test_dist.py
pycvi/tests/test_vi.py
pycvi/vi.py
pycvi_lib-0.1.5.dist-info/LICENSE.txt
pycvi_lib-0.1.5.dist-info/METADATA
pycvi_lib-0.1.5.dist-info/WHEEL
pycvi_lib-0.1.5.dist-info/RECORD
