Metadata-Version: 2.1
Name: pycvi-lib
Version: 0.1.5
Summary: Internal Cluster Validity Indices in python, compatible with time-series data
Home-page: https://pycvi.readthedocs.io/en/latest/
Author: Natacha, Galmiche
Author-email: natacha.galmiche@uib.no
Requires-Python: >=3.8,<3.12
Classifier: Programming Language :: Python :: 3
Classifier: Programming Language :: Python :: 3.8
Classifier: Programming Language :: Python :: 3.9
Classifier: Programming Language :: Python :: 3.10
Classifier: Programming Language :: Python :: 3.11
Provides-Extra: examples
Requires-Dist: aeon (>=0.10.0) ; python_version >= "3.9" and python_version < "3.12"
Requires-Dist: aeon (>=0.7.0) ; python_version >= "3.8" and python_version < "3.9"
Requires-Dist: matplotlib (>=3.7,<3.8) ; (python_version >= "3.8" and python_version < "3.9") and (extra == "examples")
Requires-Dist: matplotlib (>=3.8) ; (python_version >= "3.9" and python_version < "3.12") and (extra == "examples")
Requires-Dist: scikit-learn-extra (>=0.3.0,<0.4.0) ; (python_version >= "3.8" and python_version < "3.12") and (extra == "examples")
Project-URL: Repository, https://github.com/nglm/pycvi
